tests/__init__.py
tests/settings.py
tests/test_edit_handlers.py
tests/test_page.py
tests/test_widget.py
tests/urls.py
tests/testapp/__init__.py
tests/testapp/dynamic_functions.py
tests/testapp/models.py
tests/testapp/migrations/0001_initial.py
tests/testapp/migrations/__init__.py
wagtail_dynamic_dropdown/__init__.py
wagtail_dynamic_dropdown/apps.py
wagtail_dynamic_dropdown/edit_handlers.py
wagtail_dynamic_dropdown/widgets.py
wagtail_dynamic_dropdown/migrations/__init__.py
wagtail_dynamic_dropdown/static/wagtail_dynamic_dropdown/js/dynamic_dropdown.js
wagtail_dynamic_dropdown/static/wagtail_dynamic_dropdown/styles/dynamic_dropdown.css
wagtail_dynamic_dropdown/templates/wagtail_dynamic_dropdown/widgets/dynamic_dropdown.html
wagtail_dynamic_dropdown/templates/wagtail_dynamic_dropdown/widgets/dynamic_dropdown_input.html
wagtail_dynamic_dropdown/templates/wagtail_dynamic_dropdown/widgets/dynamic_dropdown_option.html
wagtail_dynamic_dropdown-0.0.4.dist-info/LICENSE
wagtail_dynamic_dropdown-0.0.4.dist-info/METADATA
wagtail_dynamic_dropdown-0.0.4.dist-info/WHEEL
wagtail_dynamic_dropdown-0.0.4.dist-info/top_level.txt
wagtail_dynamic_dropdown-0.0.4.dist-info/RECORD
