Metadata-Version: 2.1
Name: wagtail-dynamic-dropdown
Version: 0.0.4
Home-page: https://github.com/LilJack118/wagtail-dynamic-dropdown
Author: LilJack118
Author-email: jakub@kachange.com
Project-URL: Bug Tracker, https://github.com/LilJack118/wagtail-dynamic-dropdown/issues
Keywords: wagtail django
Classifier: Programming Language :: Python :: 3
Classifier: License :: OSI Approved :: MIT License
Classifier: Operating System :: OS Independent
License-File: LICENSE
